opennn.cp36-win_amd64.pyd
OpenNN-0.56.2.dist-info/LICENSE.txt
OpenNN-0.56.2.dist-info/METADATA
OpenNN-0.56.2.dist-info/WHEEL
OpenNN-0.56.2.dist-info/top_level.txt
OpenNN-0.56.2.dist-info/RECORD
